fastapi_tags/__init__.py
fastapi_tags/core.py
fastapi_tags/py.typed
fastapi_tags/svg.py
fastapi_tags/tags.py
fastapi_tags-0.5.1.dist-info/licenses/LICENSE
fastapi_tags-0.5.1.dist-info/METADATA
fastapi_tags-0.5.1.dist-info/WHEEL
fastapi_tags-0.5.1.dist-info/top_level.txt
fastapi_tags-0.5.1.dist-info/RECORD
