Metadata-Version: 2.4
Name: fastapi-tags
Version: 0.5.1
Summary: Adds s-expression HTML tags to FastAPI views. Inspired by FastHTML's use of fastcore's FT components.
Project-URL: homepage, https://github.com/pydanny/fastapi-tags
Project-URL: bugs, https://github.com/pydanny/fastapi-tags/issues
Classifier: Operating System :: OS Independent
Classifier: Programming Language :: Python :: 3
Classifier: Programming Language :: Python
Classifier: Topic :: Internet
Classifier: Topic :: Software Development :: Libraries :: Application Frameworks
Classifier: Topic :: Software Development :: Libraries :: Python Modules
Classifier: Topic :: Software Development :: Libraries
Classifier: Topic :: Software Development
Classifier: Typing :: Typed
Classifier: Development Status :: 4 - Beta
Classifier: Environment :: Web Environment
Classifier: Framework :: FastAPI
Classifier: Intended Audience :: Developers
Classifier: License :: OSI Approved :: MIT License
Classifier: Programming Language :: Python :: 3 :: Only
Classifier: Programming Language :: Python :: 3.10
Classifier: Programming Language :: Python :: 3.11
Classifier: Programming Language :: Python :: 3.12
Classifier: Programming Language :: Python :: 3.13
Requires-Python: >=3.10
License-File: LICENSE
Requires-Dist: fastapi>=0.115.12
Provides-Extra: dev
Requires-Dist: coverage>=7.8.2; extra == "dev"
Requires-Dist: httpx>=0.28.1; extra == "dev"
Requires-Dist: ipdb>=0.13.13; extra == "dev"
Requires-Dist: mypy>=1.16.0; extra == "dev"
Requires-Dist: pytest>=8.4.0; extra == "dev"
Requires-Dist: ruff>=0.11.13; extra == "dev"
Dynamic: license-file
